autosolve_http_client/session.py
autosolve_http_client-1.0.4.dist-info/LICENSE
autosolve_http_client-1.0.4.dist-info/METADATA
autosolve_http_client-1.0.4.dist-info/WHEEL
autosolve_http_client-1.0.4.dist-info/top_level.txt
autosolve_http_client-1.0.4.dist-info/RECORD
