Metadata-Version: 2.1
Name: autosolve-http-client
Version: 1.0.4
Summary: HTTP Client for connecting to AYCD AutoSolve network
Author: AYCD Inc
Author-email: contact@aycd.io
Classifier: Programming Language :: Python :: 3
Classifier: License :: OSI Approved :: MIT License
Classifier: Operating System :: OS Independent
Requires-Python: >=3.7
License-File: LICENSE
Requires-Dist: urllib3
